ChinesePy/ChBase.py
ChinesePy/__init__.py
ChinesePy-1.0.2.dist-info/METADATA
ChinesePy-1.0.2.dist-info/WHEEL
ChinesePy-1.0.2.dist-info/top_level.txt
ChinesePy-1.0.2.dist-info/RECORD
