Metadata-Version: 2.1
Name: ChinesePy
Version: 1.0.2
Summary: 中文函数，适合初学菜鸟……
Home-page: UNKNOWN
Author: pythonnlgs
Author-email: UNKNOWN
License: UNKNOWN
Platform: UNKNOWN
